pyreydenx/__init__.py
pyreydenx/action.py
pyreydenx/client.py
pyreydenx/exceptions.py
pyreydenx/order.py
pyreydenx/prices.py
pyreydenx/traffic.py
pyreydenx/user.py
pyreydenx/model/__init__.py
pyreydenx/model/content_type.py
pyreydenx/model/date_qty.py
pyreydenx/model/id_qty.py
pyreydenx/model/launch_params.py
pyreydenx/model/new_order_parameters.py
pyreydenx/model/online_stat.py
pyreydenx/model/order.py
pyreydenx/model/payment.py
pyreydenx/model/platform.py
pyreydenx/model/price.py
pyreydenx/model/price_category.py
pyreydenx/model/result.py
pyreydenx/model/site_stat.py
pyreydenx/model/task.py
pyreydenx/model/token.py
pyreydenx/model/traffic.py
pyreydenx/model/user.py
tests/__init__.py
tests/test_client.py
pyreydenx-1.0.10.dist-info/LICENSE
pyreydenx-1.0.10.dist-info/METADATA
pyreydenx-1.0.10.dist-info/WHEEL
pyreydenx-1.0.10.dist-info/top_level.txt
pyreydenx-1.0.10.dist-info/RECORD
