Metadata-Version: 2.1
Name: pyreydenx
Version: 1.0.10
Summary: Reyden-X is an automated service for promoting live broadcasts on external sites with integrated system of viewers and views management.
Home-page: https://github.com/pixel365/pyreydenx
Download-URL: https://github.com/pixel365/pyreydenx/archive/master.zip
Author: pixel365
Author-email: Ruslan Semagin <pixel.365.24@gmail.com>
Maintainer-email: Ruslan Semagin <pixel.365.24@gmail.com>
License: Copyright (c) 2018 The Python Packaging Authority
Project-URL: Documentation, https://api.reyden-x.com/docs
Project-URL: Source, https://github.com/pixel365/pyreydenx
Keywords: reydenx,twitch,trovo,youtube,vkplay,goodgame
Classifier: Development Status :: 5 - Production/Stable
Classifier: Intended Audience :: Developers
Classifier: License :: OSI Approved :: Apache Software License
Classifier: Programming Language :: Python :: 3 :: Only
Requires-Python: >=3.11
License-File: LICENSE
Requires-Dist: httpx <0.30,>=0.20
Requires-Dist: pydantic <3.0,>=2.0
